dictionary/__init__.py
dictionary/dictionary.py
cemre_biltekin_very_simple_dictionary-2.0.0.dist-info/METADATA
cemre_biltekin_very_simple_dictionary-2.0.0.dist-info/WHEEL
cemre_biltekin_very_simple_dictionary-2.0.0.dist-info/top_level.txt
cemre_biltekin_very_simple_dictionary-2.0.0.dist-info/RECORD
