Metadata-Version: 2.1
Name: cemre-biltekin-very-simple-dictionary
Version: 2.0.0
Summary: UNKNOWN
Author: Cemre Biltekin
License: UNKNOWN
Platform: UNKNOWN
Requires-Python: >=3.8
Requires-Dist: requests (>=2.23.0)
